flake64/__init__.py
flake64-0.1.0.dist-info/LICENSE
flake64-0.1.0.dist-info/WHEEL
flake64-0.1.0.dist-info/METADATA
flake64-0.1.0.dist-info/RECORD
