Metadata-Version: 2.1
Name: flake64
Version: 0.1.0
Summary: A squared Flake8
License: MIT
Author: Axel H.
Author-email: noirbizarre@gmail.com
Requires-Python: >=3.6
Classifier: License :: OSI Approved :: MIT License
Classifier: Programming Language :: Python :: 3
Classifier: Programming Language :: Python :: 3.6
Classifier: Programming Language :: Python :: 3.7
Classifier: Programming Language :: Python :: 3.8
Classifier: Programming Language :: Python :: 3.9
